omronfins/__init__.py
omronfins/datacreator.py
omronfins/finsudp.py
omronfins-1.0.3.dist-info/LICENSE
omronfins-1.0.3.dist-info/METADATA
omronfins-1.0.3.dist-info/WHEEL
omronfins-1.0.3.dist-info/top_level.txt
omronfins-1.0.3.dist-info/RECORD
