Metadata-Version: 2.1
Name: omronfins
Version: 1.0.3
Summary: Utilities for OMRON FINS protocol
Home-page: https://github.com/TaishiUeda/OmronFinsEthernet
Author: Taishi Ueda
Author-email: taishi.ueda@gmail.com
License: UNKNOWN
Platform: UNKNOWN
